super_code/__init__.py
super_code_clatter-0.0.2.dist-info/METADATA
super_code_clatter-0.0.2.dist-info/WHEEL
super_code_clatter-0.0.2.dist-info/top_level.txt
super_code_clatter-0.0.2.dist-info/RECORD
