Metadata-Version: 2.1
Name: super-code-clatter
Version: 0.0.2
Summary: Super-code encoder and decoder
Author: clatter
Author-email: kugel-pruefungemn0j@icloud.com
License: UNKNOWN
Platform: UNKNOWN
Classifier: Programming Language :: Python :: 3
Classifier: License :: OSI Approved :: MIT License
Classifier: Operating System :: OS Independent
Requires-Python: >=3.6
